mcp_github/__init__.py
mcp_github/server.py
mcp_github-0.0.3.dist-info/METADATA
mcp_github-0.0.3.dist-info/WHEEL
mcp_github-0.0.3.dist-info/entry_points.txt
mcp_github-0.0.3.dist-info/top_level.txt
mcp_github-0.0.3.dist-info/RECORD
