Metadata-Version: 2.4
Name: mcp-github
Version: 0.0.3
Summary: Github MCP Server for interacting with Github's API
Requires-Python: >=3.10
Requires-Dist: mcp[cli]>=1.6.0
Requires-Dist: PyGithub>=2.1.1
Requires-Dist: requests>=2.31.0
